mundi_healthcare/__init__.py
mundi_healthcare/functions.py
mundi_healthcare/databases/capacity.pkl.gz
mundi_healthcare-0.1.1.dist-info/LICENSE
mundi_healthcare-0.1.1.dist-info/WHEEL
mundi_healthcare-0.1.1.dist-info/METADATA
mundi_healthcare-0.1.1.dist-info/RECORD
